skipp/filters.cp39-win_amd64.pyd
skipp/morphology.cp39-win_amd64.pyd
skipp/transform.cp39-win_amd64.pyd
scikit_ipp-1.2.0.dist-info/LICENSE.txt
scikit_ipp-1.2.0.dist-info/METADATA
scikit_ipp-1.2.0.dist-info/WHEEL
scikit_ipp-1.2.0.dist-info/top_level.txt
scikit_ipp-1.2.0.dist-info/RECORD
