Metadata-Version: 2.1
Name: scikit-ipp
Version: 1.2.0
Summary: Image processing library powered by Intel(R) IPP
Home-page: http://github.com/IntelPython/scikit-ipp
Author: Intel Corporation
Maintainer: Intel Corp.
Maintainer-email: scripting@intel.com
License: BSD
Download-URL: http://github.com/IntelPython/scikit-ipp
Platform: Windows
Platform: Linux
Platform: Mac OS-X
Classifier: Development Status :: 5 - Production/Stable
Classifier: Intended Audience :: Science/Research
Classifier: Intended Audience :: Developers
Classifier: License :: OSI Approved
Classifier: Programming Language :: C
Classifier: Programming Language :: Python
Classifier: Programming Language :: Python :: 3.6
Classifier: Programming Language :: Python :: 3.7
Classifier: Programming Language :: Python :: 3.8
Classifier: Programming Language :: Python :: Implementation :: CPython
Classifier: Topic :: Software Development
Classifier: Topic :: Scientific/Engineering
Classifier: Operating System :: Microsoft :: Windows
Classifier: Operating System :: POSIX
Classifier: Operating System :: Unix
Classifier: Operating System :: MacOS
Requires-Python: >=3.6
License-File: LICENSE.txt
Requires-Dist: ipp
Requires-Dist: intel-openmp
Requires-Dist: numpy
